LICENCE.txt
README.txt
setup.py
helper_utils/__init__.py
helper_utils/helper.py
helper_utils.egg-info/PKG-INFO
helper_utils.egg-info/SOURCES.txt
helper_utils.egg-info/dependency_links.txt
helper_utils.egg-info/requires.txt
helper_utils.egg-info/top_level.txt